valkey/__init__.py
valkey/typing.py
valkey/utils.py
valkey_py-0.0.1.dist-info/METADATA
valkey_py-0.0.1.dist-info/WHEEL
valkey_py-0.0.1.dist-info/top_level.txt
valkey_py-0.0.1.dist-info/RECORD
