Metadata-Version: 2.1
Name: valkey-py
Version: 0.0.1
Summary: Python interface for valkey key-value store
Author-email: Siddharth Prajosh <valkey@example.com>
Project-URL: Homepage, https://github.com/sprajosh/valkey-py
Classifier: License :: OSI Approved :: MIT License
Classifier: Programming Language :: Python
Classifier: Programming Language :: Python :: 3
Requires-Python: >=3.7
Provides-Extra: dev
